hccfhir/__init__.py
hccfhir/extractor.py
hccfhir/hccfhir.py
hccfhir/data/__init__.py
hccfhir/data/sample_eob_1.json
hccfhir/data/sample_eob_2.json
hccfhir/data/sample_eob_3.json
hccfhir-0.0.9.dist-info/METADATA
hccfhir-0.0.9.dist-info/WHEEL
hccfhir-0.0.9.dist-info/licenses/LICENSE
hccfhir-0.0.9.dist-info/RECORD
