Metadata-Version: 2.3
Name: hccfhir
Version: 0.0.9
Summary: HCC Algorithm for FHIR Resources
Project-URL: Homepage, https://github.com/mimilabs/hccfhir
Project-URL: Issues, https://github.com/mimilabs/hccfhir/issues
Author-email: Yubin Park <yubin.park@mimilabs.ai>
Classifier: License :: OSI Approved :: Apache Software License
Classifier: Operating System :: OS Independent
Classifier: Programming Language :: Python :: 3
Requires-Python: >=3.8
Requires-Dist: pydantic>=2.10.3
